datalad_installer.py
datalad_installer-1.1.1.dist-info/LICENSE
datalad_installer-1.1.1.dist-info/METADATA
datalad_installer-1.1.1.dist-info/WHEEL
datalad_installer-1.1.1.dist-info/entry_points.txt
datalad_installer-1.1.1.dist-info/top_level.txt
datalad_installer-1.1.1.dist-info/RECORD
