Metadata-Version: 2.1
Name: datalad-installer
Version: 1.1.1
Summary: Installation script for Datalad and related components
Home-page: https://github.com/datalad/datalad-installer
Author: The DataLad Team and Contributors
Author-email: team@datalad.org
Maintainer: John Thorvald Wodder II
Maintainer-email: datalad-installer@varonathe.org
License: MIT
Project-URL: Source Code, https://github.com/datalad/datalad-installer
Project-URL: Bug Tracker, https://github.com/datalad/datalad-installer/issues
Keywords: apt,conda,datalad,git-annex,installer,miniconda,neurodebian
Classifier: Development Status :: 4 - Beta
Classifier: Programming Language :: Python :: 3 :: Only
Classifier: Programming Language :: Python :: 3
Classifier: Programming Language :: Python :: 3.9
Classifier: Programming Language :: Python :: 3.10
Classifier: Programming Language :: Python :: 3.11
Classifier: Programming Language :: Python :: 3.12
Classifier: Programming Language :: Python :: Implementation :: CPython
Classifier: Programming Language :: Python :: Implementation :: PyPy
Classifier: License :: OSI Approved :: MIT License
Classifier: Environment :: Console
Classifier: Intended Audience :: Developers
Classifier: Intended Audience :: Information Technology
Classifier: Intended Audience :: Science/Research
Classifier: Intended Audience :: System Administrators
Classifier: Topic :: Scientific/Engineering :: Bio-Informatics
Classifier: Topic :: System :: Installation/Setup
Classifier: Topic :: System :: Systems Administration
Requires-Python: >=3.9
License-File: LICENSE
